logstashpy/__init__.py
logstashpy/serialization.py
logstashpy-0.0.1.dist-info/LICENSE
logstashpy-0.0.1.dist-info/METADATA
logstashpy-0.0.1.dist-info/WHEEL
logstashpy-0.0.1.dist-info/top_level.txt
logstashpy-0.0.1.dist-info/RECORD
