Metadata-Version: 2.1
Name: logstashpy
Version: 0.0.1
Summary: python logging handlers to send data to Logstash server with SSL/TLS support
Home-page: https://github.com/pranavgupta1234/logstashpy
Author: Pranav Gupta
Author-email: pranavgupta4321@gmail.com
License: Apache Software License
Platform: UNKNOWN
Classifier: Intended Audience :: Developers
Classifier: Topic :: Software Development :: Build Tools
Classifier: License :: OSI Approved :: Apache Software License
Classifier: Programming Language :: Python :: 3.6
Classifier: Programming Language :: Python :: 3.7
